{
  "GET /api": {
    "description": "serves up a json representation of all the available endpoints of the api"
  },
  "GET /api/topics": {
    "description": "serves an array of all topics",
    "queries": [],
    "exampleResponse": {
      "topics": [{ "slug": "football", "description": "Footie!" }]
    }
  },
  "GET /api/articles": {
    "description": "serves an array of all topics",
    "queries": ["author", "topic", "sort_by", "order"],
    "exampleResponse": {
      "articles": [
        {
          "title": "Seafood substitutions are increasing",
          "topic": "cooking",
          "author": "weegembump",
          "body": "Text from the article..",
          "created_at": 1527695953341
        }
      ]
    }
  },
  "GET /api/articles/:article_id": {
    "description": "",
    "quieries": [],
    "exampleResponse": {}
  },
  "PATCH /api/articles/:article_id": {
    "description": "",
    "quieries": [],
    "exampleResponse": {}
  },
  "POST /api/articles/:article_id/comments": {
    "description": "",
    "quieries": [],
    "exampleResponse": {}
  },
  "GET /api/articles/:article_id/comments": {
    "description": "",
    "quieries": [],
    "exampleResponse": {}
  },
  "PATCH /api/comments/:comment_id": {
    "description": "",
    "quieries": [],
    "exampleResponse": {}
  },
  "DELETE /api/comments/:comment_id": {
    "description": "",
    "quieries": [],
    "exampleResponse": {}
  }
}
